wows_eval/__init__.py
wows_eval-0.0.6.dist-info/METADATA
wows_eval-0.0.6.dist-info/WHEEL
wows_eval-0.0.6.dist-info/entry_points.txt
wows_eval-0.0.6.dist-info/top_level.txt
wows_eval-0.0.6.dist-info/RECORD
